TOPSIS_Ankush_101803384/__init__.py
TOPSIS_Ankush_101803384-0.1.0.dist-info/Licence.txt
TOPSIS_Ankush_101803384-0.1.0.dist-info/METADATA
TOPSIS_Ankush_101803384-0.1.0.dist-info/WHEEL
TOPSIS_Ankush_101803384-0.1.0.dist-info/top_level.txt
TOPSIS_Ankush_101803384-0.1.0.dist-info/RECORD
