Metadata-Version: 2.1
Name: TOPSIS-Ankush-101803384
Version: 0.1.0
Summary: Implementation of TOPSIS
Home-page: UNKNOWN
Author: Ankush Gupta
Author-email: ankushgupta10092000@gmail.com
License: UNKNOWN
Keywords: topsis pandas rank decision_matrix
Platform: UNKNOWN
Classifier: Programming Language :: Python :: 3
Classifier: License :: OSI Approved :: MIT License
Classifier: Operating System :: OS Independent
Requires-Python: >=3.0
Requires-Dist: pandas
